{
  "id": "G-001",
  "title": "플레이어 이동 시스템 구현",
  "description": "WASD 키보드 입력으로 3D 공간에서 플레이어(큐브)를 이동시키는 기능을 구현합니다. 카메라가 플레이어를 따라가도록 합니다.",
  "status": "draft",
  "tags": ["godot", "게임", "3d"],
  "dependencies": [],
  "conditions": [
    {
      "description": "WASD로 플레이어가 상하좌우로 이동할 수 있다",
      "status": "pending"
    },
    {
      "description": "카메라가 플레이어를 따라간다",
      "status": "pending"
    },
    {
      "description": "이동 속도를 export 변수로 조절할 수 있다",
      "status": "pending"
    }
  ],
  "createdAt": "2026-03-24T05:00:00Z",
  "updatedAt": "2026-03-24T05:00:00Z"
}
